{
  "date": "2026-06-13",
  "updatedAt": "2026-07-09T11:38:55.692Z",
  "rows": [
    {
      "date": "2026-06-13",
      "project": "短线王新开",
      "channel": "APP",
      "adType": "",
      "adTypeName": "全部广告类型",
      "bannerType": 1,
      "adId": "238148",
      "title": "短线王新客今日特惠！",
      "audience": "829 - 专题测试\n1067 - 短线王新开-智行版活跃登录1-180天\n105 - 短线王新开-智行版近1天注册用户【程序定制，请勿修改】\n74 - 智行版（不能用于推送和投教直播）\n5641 - 短线王新开-智行版活跃登录181-360天",
      "popup": 0,
      "click": 3,
      "purchaseClick": 2,
      "order": 2,
      "deal": 1,
      "material": "短线王新客今日特惠！",
      "updatedAt": "2026-06-14 02:19",
      "rawId": 373323
    },
    {
      "date": "2026-06-13",
      "project": "短线王新开",
      "channel": "APP",
      "adType": "",
      "adTypeName": "全部广告类型",
      "bannerType": 1,
      "adId": "238149",
      "title": "短线王年终钜惠来袭！",
      "audience": "105 - 短线王新开-智行版近1天注册用户【程序定制，请勿修改】\n365 - 员工账号\n569 - 1个月内登录智行版客户\n829 - 专题测试\n1067 - 短线王新开-智行版活跃登录1-180天\n74 - 智行版（不能用于推送和投教直播）\n5641 - 短线王新开-智行版活跃登录181-360天",
      "popup": 0,
      "click": 7,
      "purchaseClick": 1,
      "order": 1,
      "deal": 0,
      "material": "短线王年终钜惠来袭！",
      "updatedAt": "2026-06-14 02:19",
      "rawId": 373324
    },
    {
      "date": "2026-06-13",
      "project": "短线王新开",
      "channel": "APP",
      "adType": "",
      "adTypeName": "全部广告类型",
      "bannerType": 1,
      "adId": "238150",
      "title": "新客特惠",
      "audience": "74 - 智行版（不能用于推送和投教直播）\n365 - 员工账号",
      "popup": 0,
      "click": 4,
      "purchaseClick": 0,
      "order": 0,
      "deal": 0,
      "material": "新客特惠",
      "updatedAt": "2026-06-14 02:19",
      "rawId": 373325
    },
    {
      "date": "2026-06-13",
      "project": "短线王新开",
      "channel": "APP",
      "adType": "",
      "adTypeName": "全部广告类型",
      "bannerType": 1,
      "adId": "238151",
      "title": "立即抢购",
      "audience": "105 - 短线王新开-智行版近1天注册用户【程序定制，请勿修改】\n365 - 员工账号\n1067 - 短线王新开-智行版活跃登录1-180天\n569 - 1个月内登录智行版客户\n74 - 智行版（不能用于推送和投教直播）\n5641 - 短线王新开-智行版活跃登录181-360天",
      "popup": 0,
      "click": 20,
      "purchaseClick": 6,
      "order": 4,
      "deal": 2,
      "material": "立即抢购",
      "updatedAt": "2026-06-14 02:19",
      "rawId": 373326
    },
    {
      "date": "2026-06-13",
      "project": "短线王新开",
      "channel": "APP",
      "adType": "",
      "adTypeName": "全部广告类型",
      "bannerType": 1,
      "adId": "238152",
      "title": "立即抢购",
      "audience": "365 - 员工账号\n1724 - 10天内注册的智行版\n105 - 短线王新开-智行版近1天注册用户【程序定制，请勿修改】",
      "popup": 0,
      "click": 12,
      "purchaseClick": 5,
      "order": 4,
      "deal": 3,
      "material": "立即抢购",
      "updatedAt": "2026-06-14 02:19",
      "rawId": 373327
    },
    {
      "date": "2026-06-13",
      "project": "短线王新开",
      "channel": "APP",
      "adType": "",
      "adTypeName": "全部广告类型",
      "bannerType": 1,
      "adId": "238153",
      "title": "立即抢购",
      "audience": "105 - 短线王新开-智行版近1天注册用户【程序定制，请勿修改】\n365 - 员工账号\n74 - 智行版（不能用于推送和投教直播）\n1067 - 短线王新开-智行版活跃登录1-180天\n569 - 1个月内登录智行版客户\n5641 - 短线王新开-智行版活跃登录181-360天",
      "popup": 0,
      "click": 22,
      "purchaseClick": 8,
      "order": 4,
      "deal": 2,
      "material": "立即抢购",
      "updatedAt": "2026-06-15 12:00",
      "rawId": 373328
    },
    {
      "date": "2026-06-13",
      "project": "短线王新开",
      "channel": "APP",
      "adType": "",
      "adTypeName": "全部广告类型",
      "bannerType": 1,
      "adId": "238154",
      "title": "立即抢购",
      "audience": "365 - 员工账号\n1724 - 10天内注册的智行版\n105 - 短线王新开-智行版近1天注册用户【程序定制，请勿修改】",
      "popup": 0,
      "click": 11,
      "purchaseClick": 4,
      "order": 4,
      "deal": 1,
      "material": "立即抢购",
      "updatedAt": "2026-06-14 02:19",
      "rawId": 373329
    },
    {
      "date": "2026-06-13",
      "project": "短线王新开",
      "channel": "APP",
      "adType": "",
      "adTypeName": "全部广告类型",
      "bannerType": 1,
      "adId": "238155",
      "title": "立即抢购",
      "audience": "105 - 短线王新开-智行版近1天注册用户【程序定制，请勿修改】\n365 - 员工账号\n1067 - 短线王新开-智行版活跃登录1-180天\n569 - 1个月内登录智行版客户\n74 - 智行版（不能用于推送和投教直播）\n5641 - 短线王新开-智行版活跃登录181-360天",
      "popup": 0,
      "click": 12,
      "purchaseClick": 4,
      "order": 2,
      "deal": 1,
      "material": "立即抢购",
      "updatedAt": "2026-06-14 02:19",
      "rawId": 373330
    },
    {
      "date": "2026-06-13",
      "project": "短线王新开",
      "channel": "APP",
      "adType": "",
      "adTypeName": "全部广告类型",
      "bannerType": 1,
      "adId": "238156",
      "title": "欢迎新朋友，你的专属优惠已到账！",
      "audience": "1067 - 短线王新开-智行版活跃登录1-180天\n105 - 短线王新开-智行版近1天注册用户【程序定制，请勿修改】\n569 - 1个月内登录智行版客户\n74 - 智行版（不能用于推送和投教直播）\n5641 - 短线王新开-智行版活跃登录181-360天",
      "popup": 0,
      "click": 0,
      "purchaseClick": 0,
      "order": 0,
      "deal": 0,
      "material": "欢迎新朋友，你的专属优惠",
      "updatedAt": "2026-06-10 02:19",
      "rawId": 373331
    },
    {
      "date": "2026-06-13",
      "project": "短线王新开",
      "channel": "APP",
      "adType": "",
      "adTypeName": "全部广告类型",
      "bannerType": 1,
      "adId": "238157",
      "title": "短线王新客今日特惠！",
      "audience": "1067 - 短线王新开-智行版活跃登录1-180天\n105 - 短线王新开-智行版近1天注册用户【程序定制，请勿修改】\n569 - 1个月内登录智行版客户\n74 - 智行版（不能用于推送和投教直播）\n5641 - 短线王新开-智行版活跃登录181-360天",
      "popup": 0,
      "click": 0,
      "purchaseClick": 0,
      "order": 0,
      "deal": 0,
      "material": "短线王新客今日特惠！",
      "updatedAt": "2026-06-10 02:19",
      "rawId": 373332
    },
    {
      "date": "2026-06-13",
      "project": "短线王新开",
      "channel": "APP",
      "adType": "",
      "adTypeName": "全部广告类型",
      "bannerType": 1,
      "adId": "238158",
      "title": "短线王新客今日特惠！",
      "audience": "1067 - 短线王新开-智行版活跃登录1-180天\n105 - 短线王新开-智行版近1天注册用户【程序定制，请勿修改】\n569 - 1个月内登录智行版客户\n5641 - 短线王新开-智行版活跃登录181-360天",
      "popup": 0,
      "click": 0,
      "purchaseClick": 0,
      "order": 0,
      "deal": 0,
      "material": "短线王新客今日特惠！",
      "updatedAt": "2026-06-10 02:19",
      "rawId": 373333
    },
    {
      "date": "2026-06-13",
      "project": "短线王新开",
      "channel": "APP",
      "adType": "",
      "adTypeName": "全部广告类型",
      "bannerType": 1,
      "adId": "238159",
      "title": "短线王福利",
      "audience": "1067 - 短线王新开-智行版活跃登录1-180天\n105 - 短线王新开-智行版近1天注册用户【程序定制，请勿修改】\n569 - 1个月内登录智行版客户\n74 - 智行版（不能用于推送和投教直播）\n5641 - 短线王新开-智行版活跃登录181-360天",
      "popup": 0,
      "click": 0,
      "purchaseClick": 0,
      "order": 0,
      "deal": 0,
      "material": "短线王福利",
      "updatedAt": "2026-06-10 02:19",
      "rawId": 373334
    },
    {
      "date": "2026-06-13",
      "project": "短线王新开",
      "channel": "APP",
      "adType": "",
      "adTypeName": "全部广告类型",
      "bannerType": 1,
      "adId": "238160",
      "title": "短线王福利",
      "audience": "1067 - 短线王新开-智行版活跃登录1-180天\n105 - 短线王新开-智行版近1天注册用户【程序定制，请勿修改】\n569 - 1个月内登录智行版客户\n74 - 智行版（不能用于推送和投教直播）\n5641 - 短线王新开-智行版活跃登录181-360天",
      "popup": 0,
      "click": 0,
      "purchaseClick": 0,
      "order": 0,
      "deal": 0,
      "material": "短线王福利",
      "updatedAt": "2026-06-10 02:19",
      "rawId": 373335
    },
    {
      "date": "2026-06-13",
      "project": "短线王新开",
      "channel": "APP",
      "adType": "",
      "adTypeName": "全部广告类型",
      "bannerType": 1,
      "adId": "238161",
      "title": "短线王福利",
      "audience": "1067 - 短线王新开-智行版活跃登录1-180天\n105 - 短线王新开-智行版近1天注册用户【程序定制，请勿修改】\n569 - 1个月内登录智行版客户\n74 - 智行版（不能用于推送和投教直播）\n5641 - 短线王新开-智行版活跃登录181-360天",
      "popup": 0,
      "click": 0,
      "purchaseClick": 0,
      "order": 0,
      "deal": 0,
      "material": "短线王福利",
      "updatedAt": "2026-06-10 02:19",
      "rawId": 373336
    },
    {
      "date": "2026-06-13",
      "project": "短线王新开",
      "channel": "APP",
      "adType": "",
      "adTypeName": "全部广告类型",
      "bannerType": 1,
      "adId": "238162",
      "title": "短线王福利",
      "audience": "1067 - 短线王新开-智行版活跃登录1-180天\n105 - 短线王新开-智行版近1天注册用户【程序定制，请勿修改】\n569 - 1个月内登录智行版客户\n74 - 智行版（不能用于推送和投教直播）\n5641 - 短线王新开-智行版活跃登录181-360天",
      "popup": 0,
      "click": 0,
      "purchaseClick": 0,
      "order": 0,
      "deal": 0,
      "material": "短线王福利",
      "updatedAt": "2026-06-10 02:19",
      "rawId": 373337
    },
    {
      "date": "2026-06-13",
      "project": "短线王新开",
      "channel": "APP",
      "adType": "",
      "adTypeName": "全部广告类型",
      "bannerType": 1,
      "adId": "238163",
      "title": "短线王福利",
      "audience": "1067 - 短线王新开-智行版活跃登录1-180天\n105 - 短线王新开-智行版近1天注册用户【程序定制，请勿修改】\n569 - 1个月内登录智行版客户\n74 - 智行版（不能用于推送和投教直播）\n5641 - 短线王新开-智行版活跃登录181-360天",
      "popup": 0,
      "click": 0,
      "purchaseClick": 0,
      "order": 0,
      "deal": 0,
      "material": "短线王福利",
      "updatedAt": "2026-06-10 02:19",
      "rawId": 373338
    },
    {
      "date": "2026-06-13",
      "project": "短线王新开",
      "channel": "APP",
      "adType": "",
      "adTypeName": "全部广告类型",
      "bannerType": 1,
      "adId": "238164",
      "title": "短线王特惠",
      "audience": "1067 - 短线王新开-智行版活跃登录1-180天\n105 - 短线王新开-智行版近1天注册用户【程序定制，请勿修改】\n5641 - 短线王新开-智行版活跃登录181-360天",
      "popup": 0,
      "click": 0,
      "purchaseClick": 0,
      "order": 0,
      "deal": 0,
      "material": "短线王特惠",
      "updatedAt": "2026-06-10 02:19",
      "rawId": 373339
    },
    {
      "date": "2026-06-13",
      "project": "短线王新开",
      "channel": "APP",
      "adType": "",
      "adTypeName": "全部广告类型",
      "bannerType": 1,
      "adId": "238165",
      "title": "新客福利",
      "audience": "1067 - 短线王新开-智行版活跃登录1-180天\n365 - 员工账号\n105 - 短线王新开-智行版近1天注册用户【程序定制，请勿修改】\n569 - 1个月内登录智行版客户\n74 - 智行版（不能用于推送和投教直播）\n5641 - 短线王新开-智行版活跃登录181-360天",
      "popup": 0,
      "click": 0,
      "purchaseClick": 0,
      "order": 0,
      "deal": 0,
      "material": "新客福利",
      "updatedAt": "2026-06-10 02:19",
      "rawId": 373340
    },
    {
      "date": "2026-06-13",
      "project": "短线王新开",
      "channel": "APP",
      "adType": "",
      "adTypeName": "全部广告类型",
      "bannerType": 1,
      "adId": "238166",
      "title": "新客福利",
      "audience": "1067 - 短线王新开-智行版活跃登录1-180天\n365 - 员工账号\n105 - 短线王新开-智行版近1天注册用户【程序定制，请勿修改】\n569 - 1个月内登录智行版客户\n74 - 智行版（不能用于推送和投教直播）\n5641 - 短线王新开-智行版活跃登录181-360天",
      "popup": 0,
      "click": 0,
      "purchaseClick": 0,
      "order": 0,
      "deal": 0,
      "material": "新客福利",
      "updatedAt": "2026-06-10 02:19",
      "rawId": 373341
    },
    {
      "date": "2026-06-13",
      "project": "短线王新开",
      "channel": "APP",
      "adType": "",
      "adTypeName": "全部广告类型",
      "bannerType": 1,
      "adId": "238167",
      "title": "专属选股器+买卖信号",
      "audience": "105 - 短线王新开-智行版近1天注册用户【程序定制，请勿修改】\n365 - 员工账号\n1067 - 短线王新开-智行版活跃登录1-180天\n569 - 1个月内登录智行版客户\n74 - 智行版（不能用于推送和投教直播）\n5641 - 短线王新开-智行版活跃登录181-360天",
      "popup": 0,
      "click": 4,
      "purchaseClick": 1,
      "order": 1,
      "deal": 0,
      "material": "专属选股器+买卖信号",
      "updatedAt": "2026-06-14 02:19",
      "rawId": 373342
    },
    {
      "date": "2026-06-13",
      "project": "短线王新开",
      "channel": "APP",
      "adType": "",
      "adTypeName": "全部广告类型",
      "bannerType": 1,
      "adId": "248058",
      "title": "短线王特惠",
      "audience": "1067 - 短线王新开-智行版活跃登录1-180天\n2962 - 智行版首次登录用户-5\n569 - 1个月内登录智行版客户\n74 - 智行版（不能用于推送和投教直播）\n5641 - 短线王新开-智行版活跃登录181-360天",
      "popup": 0,
      "click": 0,
      "purchaseClick": 0,
      "order": 0,
      "deal": 0,
      "material": "短线王特惠",
      "updatedAt": "2026-06-08 02:33",
      "rawId": 381670
    },
    {
      "date": "2026-06-13",
      "project": "短线王新开",
      "channel": "APP",
      "adType": "",
      "adTypeName": "全部广告类型",
      "bannerType": 1,
      "adId": "248059",
      "title": "短线王特惠",
      "audience": "1067 - 短线王新开-智行版活跃登录1-180天\n2962 - 智行版首次登录用户-5\n569 - 1个月内登录智行版客户\n74 - 智行版（不能用于推送和投教直播）\n5641 - 短线王新开-智行版活跃登录181-360天",
      "popup": 0,
      "click": 6,
      "purchaseClick": 2,
      "order": 2,
      "deal": 0,
      "material": "短线王特惠",
      "updatedAt": "2026-06-14 02:22",
      "rawId": 381671
    },
    {
      "date": "2026-06-13",
      "project": "短线王新开",
      "channel": "APP",
      "adType": "",
      "adTypeName": "全部广告类型",
      "bannerType": 1,
      "adId": "248307",
      "title": "短线王新客今日特惠",
      "audience": "105 - 短线王新开-智行版近1天注册用户【程序定制，请勿修改】\n1067 - 短线王新开-智行版活跃登录1-180天\n74 - 智行版（不能用于推送和投教直播）\n365 - 员工账号\n5641 - 短线王新开-智行版活跃登录181-360天",
      "popup": 0,
      "click": 1,
      "purchaseClick": 1,
      "order": 0,
      "deal": 0,
      "material": "短线王新客今日特惠",
      "updatedAt": "2026-06-14 02:22",
      "rawId": 382443
    },
    {
      "date": "2026-06-13",
      "project": "短线王新开",
      "channel": "APP",
      "adType": "",
      "adTypeName": "全部广告类型",
      "bannerType": 2,
      "adId": "250928",
      "title": "短线王限时特惠",
      "audience": "105 - 短线王新开-智行版近1天注册用户【程序定制，请勿修改】\n829 - 专题测试\n1067 - 短线王新开-智行版活跃登录1-180天\n74 - 智行版（不能用于推送和投教直播）",
      "popup": 1458,
      "click": 191,
      "purchaseClick": 16,
      "order": 12,
      "deal": 0,
      "material": "短线王限时特惠",
      "updatedAt": "2026-06-14 02:29",
      "rawId": 386063
    },
    {
      "date": "2026-06-13",
      "project": "短线王新开",
      "channel": "APP",
      "adType": "",
      "adTypeName": "全部广告类型",
      "bannerType": 2,
      "adId": "250929",
      "title": "涨停复制战法",
      "audience": "105 - 短线王新开-智行版近1天注册用户【程序定制，请勿修改】\n793 - 短线王新开-智行版新客7-30天\n74 - 智行版（不能用于推送和投教直播）",
      "popup": 88,
      "click": 12,
      "purchaseClick": 6,
      "order": 3,
      "deal": 0,
      "material": "涨停复制战法",
      "updatedAt": "2026-06-14 02:29",
      "rawId": 386064
    },
    {
      "date": "2026-06-13",
      "project": "短线王新开",
      "channel": "APP",
      "adType": "",
      "adTypeName": "全部广告类型",
      "bannerType": 2,
      "adId": "250930",
      "title": "智能选股",
      "audience": "105 - 短线王新开-智行版近1天注册用户【程序定制，请勿修改】\n829 - 专题测试\n1067 - 短线王新开-智行版活跃登录1-180天\n74 - 智行版（不能用于推送和投教直播）",
      "popup": 13,
      "click": 3,
      "purchaseClick": 0,
      "order": 0,
      "deal": 0,
      "material": "智能选股",
      "updatedAt": "2026-06-14 02:29",
      "rawId": 386065
    },
    {
      "date": "2026-06-13",
      "project": "短线王新开",
      "channel": "APP",
      "adType": "",
      "adTypeName": "全部广告类型",
      "bannerType": 2,
      "adId": "250931",
      "title": "买卖点提示",
      "audience": "105 - 短线王新开-智行版近1天注册用户【程序定制，请勿修改】\n829 - 专题测试\n1067 - 短线王新开-智行版活跃登录1-180天\n74 - 智行版（不能用于推送和投教直播）",
      "popup": 579,
      "click": 90,
      "purchaseClick": 8,
      "order": 6,
      "deal": 3,
      "material": "买卖点提示",
      "updatedAt": "2026-06-14 02:29",
      "rawId": 386066
    },
    {
      "date": "2026-06-13",
      "project": "短线王新开",
      "channel": "APP",
      "adType": "",
      "adTypeName": "全部广告类型",
      "bannerType": 2,
      "adId": "250932",
      "title": "看买点做低吸",
      "audience": "105 - 短线王新开-智行版近1天注册用户【程序定制，请勿修改】\n829 - 专题测试\n1067 - 短线王新开-智行版活跃登录1-180天\n74 - 智行版（不能用于推送和投教直播）",
      "popup": 36,
      "click": 6,
      "purchaseClick": 0,
      "order": 0,
      "deal": 0,
      "material": "看买点做低吸",
      "updatedAt": "2026-06-14 02:29",
      "rawId": 386067
    },
    {
      "date": "2026-06-13",
      "project": "短线王新开",
      "channel": "APP",
      "adType": "",
      "adTypeName": "全部广告类型",
      "bannerType": 2,
      "adId": "250933",
      "title": "抄底机会这么看",
      "audience": "105 - 短线王新开-智行版近1天注册用户【程序定制，请勿修改】\n829 - 专题测试\n1067 - 短线王新开-智行版活跃登录1-180天\n74 - 智行版（不能用于推送和投教直播）",
      "popup": 969,
      "click": 101,
      "purchaseClick": 14,
      "order": 12,
      "deal": 0,
      "material": "抄底机会这么看",
      "updatedAt": "2026-06-14 02:29",
      "rawId": 386068
    },
    {
      "date": "2026-06-13",
      "project": "短线王新开",
      "channel": "APP",
      "adType": "",
      "adTypeName": "全部广告类型",
      "bannerType": 2,
      "adId": "250934",
      "title": "一键筛选资金买入牛股",
      "audience": "105 - 短线王新开-智行版近1天注册用户【程序定制，请勿修改】\n829 - 专题测试\n1067 - 短线王新开-智行版活跃登录1-180天\n74 - 智行版（不能用于推送和投教直播）",
      "popup": 77,
      "click": 3,
      "purchaseClick": 0,
      "order": 0,
      "deal": 0,
      "material": "一键筛选资金买入牛股",
      "updatedAt": "2026-06-14 02:29",
      "rawId": 386069
    },
    {
      "date": "2026-06-13",
      "project": "短线王新开",
      "channel": "APP",
      "adType": "",
      "adTypeName": "全部广告类型",
      "bannerType": 2,
      "adId": "250935",
      "title": "短线王年终钜惠",
      "audience": "105 - 短线王新开-智行版近1天注册用户【程序定制，请勿修改】\n829 - 专题测试\n1067 - 短线王新开-智行版活跃登录1-180天\n74 - 智行版（不能用于推送和投教直播）",
      "popup": 1185,
      "click": 62,
      "purchaseClick": 5,
      "order": 3,
      "deal": 0,
      "material": "短线王年终钜惠",
      "updatedAt": "2026-06-14 02:29",
      "rawId": 386070
    },
    {
      "date": "2026-06-13",
      "project": "短线王新开",
      "channel": "APP",
      "adType": "",
      "adTypeName": "全部广告类型",
      "bannerType": 2,
      "adId": "250936",
      "title": "小白也能掌握的买点信号",
      "audience": "105 - 短线王新开-智行版近1天注册用户【程序定制，请勿修改】\n829 - 专题测试\n1067 - 短线王新开-智行版活跃登录1-180天\n74 - 智行版（不能用于推送和投教直播）",
      "popup": 95,
      "click": 11,
      "purchaseClick": 0,
      "order": 0,
      "deal": 0,
      "material": "小白也能掌握的买点信号",
      "updatedAt": "2026-06-14 02:29",
      "rawId": 386071
    },
    {
      "date": "2026-06-13",
      "project": "短线王新开",
      "channel": "APP",
      "adType": "",
      "adTypeName": "全部广告类型",
      "bannerType": 3,
      "adId": "66710",
      "title": "【短线王】基于本周资金异动已为你筛出3只潜力股",
      "audience": "1067 - 短线王新开-智行版活跃登录1-180天\n105 - 短线王新开-智行版近1天注册用户【程序定制，请勿修改】\n829 - 专题测试\n1049 - 短线王新开-1周内登录智行版客户\n5641 - 短线王新开-智行版活跃登录181-360天",
      "popup": 2639,
      "click": 135,
      "purchaseClick": 36,
      "order": 32,
      "deal": 0,
      "material": "【短线王】基于本周资金异",
      "updatedAt": "2026-06-14 12:13",
      "rawId": 385923
    },
    {
      "date": "2026-06-13",
      "project": "短线王新开",
      "channel": "APP",
      "adType": "",
      "adTypeName": "全部广告类型",
      "bannerType": 3,
      "adId": "66711",
      "title": "【周末充电】",
      "audience": "1067 - 短线王新开-智行版活跃登录1-180天\n105 - 短线王新开-智行版近1天注册用户【程序定制，请勿修改】\n829 - 专题测试\n5641 - 短线王新开-智行版活跃登录181-360天",
      "popup": 2005,
      "click": 64,
      "purchaseClick": 6,
      "order": 4,
      "deal": 1,
      "material": "【周末充电】",
      "updatedAt": "2026-06-14 12:13",
      "rawId": 386169
    },
    {
      "date": "2026-06-13",
      "project": "短线王新开",
      "channel": "APP",
      "adType": "",
      "adTypeName": "全部广告类型",
      "bannerType": 3,
      "adId": "66712",
      "title": "没时间选股？交给【短线王】",
      "audience": "1067 - 短线王新开-智行版活跃登录1-180天\n105 - 短线王新开-智行版近1天注册用户【程序定制，请勿修改】\n829 - 专题测试\n5641 - 短线王新开-智行版活跃登录181-360天",
      "popup": 1972,
      "click": 57,
      "purchaseClick": 3,
      "order": 3,
      "deal": 0,
      "material": "没时间选股？交给【短线王",
      "updatedAt": "2026-06-14 12:13",
      "rawId": 386170
    },
    {
      "date": "2026-06-13",
      "project": "短线王新开",
      "channel": "APP",
      "adType": "",
      "adTypeName": "全部广告类型",
      "bannerType": 3,
      "adId": "66713",
      "title": "短线王紧急提醒！",
      "audience": "1067 - 短线王新开-智行版活跃登录1-180天\n105 - 短线王新开-智行版近1天注册用户【程序定制，请勿修改】\n829 - 专题测试\n5641 - 短线王新开-智行版活跃登录181-360天",
      "popup": 1983,
      "click": 62,
      "purchaseClick": 1,
      "order": 1,
      "deal": 0,
      "material": "短线王紧急提醒！",
      "updatedAt": "2026-06-14 12:13",
      "rawId": 386171
    },
    {
      "date": "2026-06-13",
      "project": "短线王新开",
      "channel": "PC",
      "adType": "",
      "adTypeName": "全部广告类型",
      "bannerType": 4,
      "adId": "105367",
      "title": "0基础也能学会短线王",
      "audience": "2068 - 最近5-6天新成交短线王用户",
      "popup": 17,
      "click": 3,
      "purchaseClick": 1,
      "order": 1,
      "deal": 0,
      "material": "0基础也能学会短线王",
      "updatedAt": "2026-06-13 12:17",
      "rawId": 385963
    },
    {
      "date": "2026-06-13",
      "project": "短线王新开",
      "channel": "PC",
      "adType": "",
      "adTypeName": "全部广告类型",
      "bannerType": 4,
      "adId": "105368",
      "title": "0基础也能学会短线王",
      "audience": "2069 - 最近7-8天新成交短线王用户",
      "popup": 9,
      "click": 1,
      "purchaseClick": 0,
      "order": 0,
      "deal": 0,
      "material": "0基础也能学会短线王",
      "updatedAt": "2026-06-13 12:17",
      "rawId": 385964
    },
    {
      "date": "2026-06-13",
      "project": "短线王新开",
      "channel": "PC",
      "adType": "",
      "adTypeName": "全部广告类型",
      "bannerType": 4,
      "adId": "105369",
      "title": "0基础也能学会短线王",
      "audience": "2070 - 最近9-10天新成交短线王用户",
      "popup": 10,
      "click": 0,
      "purchaseClick": 0,
      "order": 0,
      "deal": 0,
      "material": "0基础也能学会短线王",
      "updatedAt": "2026-06-13 12:17",
      "rawId": 385965
    },
    {
      "date": "2026-06-13",
      "project": "短线王新开",
      "channel": "PC",
      "adType": "",
      "adTypeName": "全部广告类型",
      "bannerType": 4,
      "adId": "105370",
      "title": "0基础也能学会短线王",
      "audience": "2071 - 最近11-12天新成交短线王用户",
      "popup": 15,
      "click": 1,
      "purchaseClick": 0,
      "order": 0,
      "deal": 0,
      "material": "0基础也能学会短线王",
      "updatedAt": "2026-06-13 12:17",
      "rawId": 385966
    },
    {
      "date": "2026-06-13",
      "project": "短线王新开",
      "channel": "PC",
      "adType": "",
      "adTypeName": "全部广告类型",
      "bannerType": 4,
      "adId": "105371",
      "title": "0基础也能学会短线王",
      "audience": "2072 - 最近13-14天新成交短线王用户",
      "popup": 7,
      "click": 1,
      "purchaseClick": 0,
      "order": 0,
      "deal": 0,
      "material": "0基础也能学会短线王",
      "updatedAt": "2026-06-13 12:17",
      "rawId": 385967
    },
    {
      "date": "2026-06-13",
      "project": "短线王新开",
      "channel": "PC",
      "adType": "",
      "adTypeName": "全部广告类型",
      "bannerType": 4,
      "adId": "105372",
      "title": "0基础也能学会短线王",
      "audience": "2073 - 最近15-16天新成交短线王用户",
      "popup": 14,
      "click": 1,
      "purchaseClick": 0,
      "order": 0,
      "deal": 0,
      "material": "0基础也能学会短线王",
      "updatedAt": "2026-06-13 12:17",
      "rawId": 385968
    },
    {
      "date": "2026-06-13",
      "project": "短线王新开",
      "channel": "PC",
      "adType": "",
      "adTypeName": "全部广告类型",
      "bannerType": 4,
      "adId": "105373",
      "title": "0基础也能学会短线王",
      "audience": "2066 - 前2天-今天成交短线王用户",
      "popup": 45,
      "click": 10,
      "purchaseClick": 0,
      "order": 0,
      "deal": 0,
      "material": "0基础也能学会短线王",
      "updatedAt": "2026-06-14 02:34",
      "rawId": 386210
    },
    {
      "date": "2026-06-13",
      "project": "短线王新开",
      "channel": "PC",
      "adType": "",
      "adTypeName": "全部广告类型",
      "bannerType": 4,
      "adId": "105374",
      "title": "0基础也能学会短线王",
      "audience": "2067 - 最近3-4天新成交短线王用户",
      "popup": 19,
      "click": 2,
      "purchaseClick": 0,
      "order": 0,
      "deal": 0,
      "material": "0基础也能学会短线王",
      "updatedAt": "2026-06-13 12:17",
      "rawId": 385969
    },
    {
      "date": "2026-06-13",
      "project": "短线王新开",
      "channel": "PC",
      "adType": "",
      "adTypeName": "全部广告类型",
      "bannerType": 4,
      "adId": "105375",
      "title": "短线王轻松应对震荡！",
      "audience": "105 - 短线王新开-智行版近1天注册用户【程序定制，请勿修改】\n569 - 1个月内登录智行版客户\n829 - 专题测试\n1067 - 短线王新开-智行版活跃登录1-180天",
      "popup": 427,
      "click": 10,
      "purchaseClick": 0,
      "order": 0,
      "deal": 0,
      "material": "短线王轻松应对震荡！",
      "updatedAt": "2026-06-13 12:17",
      "rawId": 385885
    },
    {
      "date": "2026-06-13",
      "project": "短线王新开",
      "channel": "PC",
      "adType": "",
      "adTypeName": "全部广告类型",
      "bannerType": 4,
      "adId": "105376",
      "title": "短线王特惠来袭！",
      "audience": "105 - 短线王新开-智行版近1天注册用户【程序定制，请勿修改】\n829 - 专题测试\n1049 - 短线王新开-1周内登录智行版客户\n1067 - 短线王新开-智行版活跃登录1-180天\n1099 - 近30天注册的智行版",
      "popup": 564,
      "click": 13,
      "purchaseClick": 0,
      "order": 0,
      "deal": 0,
      "material": "短线王特惠来袭！",
      "updatedAt": "2026-06-13 12:17",
      "rawId": 385970
    },
    {
      "date": "2026-06-13",
      "project": "短线王新开",
      "channel": "PC",
      "adType": "",
      "adTypeName": "全部广告类型",
      "bannerType": 4,
      "adId": "105377",
      "title": "盘中机会把握",
      "audience": "105 - 短线王新开-智行版近1天注册用户【程序定制，请勿修改】\n829 - 专题测试\n1049 - 短线王新开-1周内登录智行版客户\n1067 - 短线王新开-智行版活跃登录1-180天",
      "popup": 422,
      "click": 6,
      "purchaseClick": 1,
      "order": 0,
      "deal": 0,
      "material": "盘中机会把握",
      "updatedAt": "2026-06-14 02:34",
      "rawId": 385971
    },
    {
      "date": "2026-06-13",
      "project": "短线王新开",
      "channel": "PC",
      "adType": "",
      "adTypeName": "全部广告类型",
      "bannerType": 4,
      "adId": "105378",
      "title": "短线王买卖点信号提示",
      "audience": "105 - 短线王新开-智行版近1天注册用户【程序定制，请勿修改】\n1049 - 短线王新开-1周内登录智行版客户\n1067 - 短线王新开-智行版活跃登录1-180天",
      "popup": 392,
      "click": 9,
      "purchaseClick": 0,
      "order": 0,
      "deal": 0,
      "material": "短线王买卖点信号提示",
      "updatedAt": "2026-06-14 02:34",
      "rawId": 386211
    },
    {
      "date": "2026-06-13",
      "project": "短线王新开",
      "channel": "PC",
      "adType": "",
      "adTypeName": "全部广告类型",
      "bannerType": 4,
      "adId": "105379",
      "title": "三板斧抓牛股",
      "audience": "105 - 短线王新开-智行版近1天注册用户【程序定制，请勿修改】\n791 - 短线王新开-智行版新客1-3天\n792 - 短线王新开-智行版新客4-7天\n793 - 短线王新开-智行版新客7-30天\n1067 - 短线王新开-智行版活跃登录1-180天",
      "popup": 156,
      "click": 4,
      "purchaseClick": 1,
      "order": 1,
      "deal": 1,
      "material": "三板斧抓牛股",
      "updatedAt": "2026-06-14 02:34",
      "rawId": 386212
    },
    {
      "date": "2026-06-13",
      "project": "短线王新开",
      "channel": "PC",
      "adType": "",
      "adTypeName": "全部广告类型",
      "bannerType": 4,
      "adId": "105380",
      "title": "涨停机会把握",
      "audience": "105 - 短线王新开-智行版近1天注册用户【程序定制，请勿修改】\n791 - 短线王新开-智行版新客1-3天\n792 - 短线王新开-智行版新客4-7天\n793 - 短线王新开-智行版新客7-30天\n1049 - 短线王新开-1周内登录智行版客户\n1067 - 短线王新开-智行版活跃登录1-180天",
      "popup": 586,
      "click": 19,
      "purchaseClick": 1,
      "order": 1,
      "deal": 0,
      "material": "涨停机会把握",
      "updatedAt": "2026-06-14 02:34",
      "rawId": 386213
    },
    {
      "date": "2026-06-13",
      "project": "短线王新开",
      "channel": "PC",
      "adType": "",
      "adTypeName": "全部广告类型",
      "bannerType": 4,
      "adId": "105381",
      "title": "短线王新客今日特惠",
      "audience": "105 - 短线王新开-智行版近1天注册用户【程序定制，请勿修改】\n791 - 短线王新开-智行版新客1-3天\n792 - 短线王新开-智行版新客4-7天\n793 - 短线王新开-智行版新客7-30天\n829 - 专题测试\n1049 - 短线王新开-1周内登录智行版客户\n1067 - 短线王新开-智行版活跃登录1-180天",
      "popup": 566,
      "click": 15,
      "purchaseClick": 0,
      "order": 0,
      "deal": 0,
      "material": "短线王新客今日特惠",
      "updatedAt": "2026-06-14 02:34",
      "rawId": 386214
    },
    {
      "date": "2026-06-13",
      "project": "短线王新开",
      "channel": "PC",
      "adType": "",
      "adTypeName": "全部广告类型",
      "bannerType": 4,
      "adId": "105382",
      "title": "【注意】",
      "audience": "105 - 短线王新开-智行版近1天注册用户【程序定制，请勿修改】\n569 - 1个月内登录智行版客户\n829 - 专题测试\n1067 - 短线王新开-智行版活跃登录1-180天",
      "popup": 585,
      "click": 6,
      "purchaseClick": 0,
      "order": 0,
      "deal": 0,
      "material": "【注意】",
      "updatedAt": "2026-06-14 02:34",
      "rawId": 385972
    },
    {
      "date": "2026-06-13",
      "project": "短线王续费",
      "channel": "APP",
      "adType": "",
      "adTypeName": "全部广告类型",
      "bannerType": 1,
      "adId": "239091",
      "title": "您的软件将到期，点击续费",
      "audience": "1454 - 营销策划测试分组\n4324 - 【短线王续费】1天后当天过期用户",
      "popup": 0,
      "click": 0,
      "purchaseClick": 0,
      "order": 0,
      "deal": 0,
      "material": "您的软件将到期，点击续费",
      "updatedAt": "2026-06-01 12:16",
      "rawId": 374046
    },
    {
      "date": "2026-06-13",
      "project": "短线王续费",
      "channel": "APP",
      "adType": "",
      "adTypeName": "全部广告类型",
      "bannerType": 1,
      "adId": "239092",
      "title": "您的软件将到期，点击续费",
      "audience": "1454 - 营销策划测试分组\n4325 - 【短线王续费】2天后当天过期用户",
      "popup": 0,
      "click": 0,
      "purchaseClick": 0,
      "order": 0,
      "deal": 0,
      "material": "您的软件将到期，点击续费",
      "updatedAt": "2026-06-01 12:16",
      "rawId": 374047
    },
    {
      "date": "2026-06-13",
      "project": "短线王续费",
      "channel": "APP",
      "adType": "",
      "adTypeName": "全部广告类型",
      "bannerType": 1,
      "adId": "239093",
      "title": "您的软件将到期，点击续费",
      "audience": "1454 - 营销策划测试分组\n4326 - 【短线王续费】3天后当天过期用户",
      "popup": 0,
      "click": 0,
      "purchaseClick": 0,
      "order": 0,
      "deal": 0,
      "material": "您的软件将到期，点击续费",
      "updatedAt": "2026-06-01 12:16",
      "rawId": 374048
    },
    {
      "date": "2026-06-13",
      "project": "短线王续费",
      "channel": "APP",
      "adType": "",
      "adTypeName": "全部广告类型",
      "bannerType": 1,
      "adId": "239094",
      "title": "您的软件将到期，点击续费",
      "audience": "1454 - 营销策划测试分组\n1993 - 【短线王续费】7天后过期用户",
      "popup": 0,
      "click": 0,
      "purchaseClick": 0,
      "order": 0,
      "deal": 0,
      "material": "您的软件将到期，点击续费",
      "updatedAt": "2026-06-01 12:16",
      "rawId": 374049
    },
    {
      "date": "2026-06-13",
      "project": "短线王续费",
      "channel": "APP",
      "adType": "",
      "adTypeName": "全部广告类型",
      "bannerType": 1,
      "adId": "239095",
      "title": "您的软件将到期，点击续费",
      "audience": "1454 - 营销策划测试分组\n1990 - 【短线王续费】30天后过期用户",
      "popup": 0,
      "click": 0,
      "purchaseClick": 0,
      "order": 0,
      "deal": 0,
      "material": "您的软件将到期，点击续费",
      "updatedAt": "2026-06-01 12:16",
      "rawId": 374050
    },
    {
      "date": "2026-06-13",
      "project": "短线王续费",
      "channel": "APP",
      "adType": "",
      "adTypeName": "全部广告类型",
      "bannerType": 1,
      "adId": "239096",
      "title": "您的软件将到期，点击续费",
      "audience": "1454 - 营销策划测试分组\n1989 - 【短线王续费】60天后过期用户",
      "popup": 0,
      "click": 0,
      "purchaseClick": 0,
      "order": 0,
      "deal": 0,
      "material": "您的软件将到期，点击续费",
      "updatedAt": "2026-06-01 12:16",
      "rawId": 374051
    },
    {
      "date": "2026-06-13",
      "project": "短线王续费",
      "channel": "APP",
      "adType": "",
      "adTypeName": "全部广告类型",
      "bannerType": 1,
      "adId": "239097",
      "title": "您的软件将到期，点击续费",
      "audience": "1454 - 营销策划测试分组\n1988 - 【短线王续费】90天后过期用户",
      "popup": 0,
      "click": 0,
      "purchaseClick": 0,
      "order": 0,
      "deal": 0,
      "material": "您的软件将到期，点击续费",
      "updatedAt": "2026-06-01 12:16",
      "rawId": 374052
    },
    {
      "date": "2026-06-13",
      "project": "短线王续费",
      "channel": "APP",
      "adType": "",
      "adTypeName": "全部广告类型",
      "bannerType": 1,
      "adId": "239098",
      "title": "您的软件将到期，点击续费",
      "audience": "1454 - 营销策划测试分组\n613 - 短线王已过期用户",
      "popup": 0,
      "click": 3,
      "purchaseClick": 0,
      "order": 0,
      "deal": 0,
      "material": "您的软件将到期，点击续费",
      "updatedAt": "2026-06-14 02:20",
      "rawId": 374053
    },
    {
      "date": "2026-06-13",
      "project": "短线王续费",
      "channel": "APP",
      "adType": "",
      "adTypeName": "全部广告类型",
      "bannerType": 1,
      "adId": "239099",
      "title": "短线王续费",
      "audience": "851 - 日常测试\n872 - 短线王续费近120天到期",
      "popup": 0,
      "click": 0,
      "purchaseClick": 0,
      "order": 0,
      "deal": 0,
      "material": "短线王续费",
      "updatedAt": "2026-06-10 02:21",
      "rawId": 374054
    },
    {
      "date": "2026-06-13",
      "project": "短线王续费",
      "channel": "APP",
      "adType": "",
      "adTypeName": "全部广告类型",
      "bannerType": 1,
      "adId": "239100",
      "title": "短线王续费",
      "audience": "851 - 日常测试\n872 - 短线王续费近120天到期",
      "popup": 0,
      "click": 0,
      "purchaseClick": 0,
      "order": 0,
      "deal": 0,
      "material": "短线王续费",
      "updatedAt": "2026-06-10 02:21",
      "rawId": 374055
    },
    {
      "date": "2026-06-13",
      "project": "短线王续费",
      "channel": "APP",
      "adType": "",
      "adTypeName": "全部广告类型",
      "bannerType": 1,
      "adId": "239101",
      "title": "短线王续费",
      "audience": "851 - 日常测试\n872 - 短线王续费近120天到期",
      "popup": 0,
      "click": 0,
      "purchaseClick": 0,
      "order": 0,
      "deal": 0,
      "material": "短线王续费",
      "updatedAt": "2026-06-10 02:21",
      "rawId": 374056
    },
    {
      "date": "2026-06-13",
      "project": "短线王续费",
      "channel": "APP",
      "adType": "",
      "adTypeName": "全部广告类型",
      "bannerType": 1,
      "adId": "239102",
      "title": "短线王续费",
      "audience": "851 - 日常测试\n872 - 短线王续费近120天到期",
      "popup": 0,
      "click": 1,
      "purchaseClick": 0,
      "order": 0,
      "deal": 0,
      "material": "短线王续费",
      "updatedAt": "2026-06-13 12:01",
      "rawId": 374057
    },
    {
      "date": "2026-06-13",
      "project": "短线王续费",
      "channel": "APP",
      "adType": "",
      "adTypeName": "全部广告类型",
      "bannerType": 1,
      "adId": "239103",
      "title": "短线王续费",
      "audience": "851 - 日常测试\n872 - 短线王续费近120天到期",
      "popup": 0,
      "click": 0,
      "purchaseClick": 0,
      "order": 0,
      "deal": 0,
      "material": "短线王续费",
      "updatedAt": "2026-06-10 02:21",
      "rawId": 374058
    },
    {
      "date": "2026-06-13",
      "project": "短线王续费",
      "channel": "APP",
      "adType": "",
      "adTypeName": "全部广告类型",
      "bannerType": 1,
      "adId": "239104",
      "title": "短线王续费",
      "audience": "851 - 日常测试\n872 - 短线王续费近120天到期",
      "popup": 0,
      "click": 0,
      "purchaseClick": 0,
      "order": 0,
      "deal": 0,
      "material": "短线王续费",
      "updatedAt": "2026-06-10 02:21",
      "rawId": 374059
    },
    {
      "date": "2026-06-13",
      "project": "短线王续费",
      "channel": "APP",
      "adType": "",
      "adTypeName": "全部广告类型",
      "bannerType": 1,
      "adId": "239105",
      "title": "续费送好礼，福利直接领",
      "audience": "851 - 日常测试\n872 - 短线王续费近120天到期",
      "popup": 0,
      "click": 0,
      "purchaseClick": 0,
      "order": 0,
      "deal": 0,
      "material": "续费送好礼，福利直接领",
      "updatedAt": "2026-06-10 02:21",
      "rawId": 374060
    },
    {
      "date": "2026-06-13",
      "project": "短线王续费",
      "channel": "APP",
      "adType": "",
      "adTypeName": "全部广告类型",
      "bannerType": 1,
      "adId": "239106",
      "title": "续费送好礼，福利直接领",
      "audience": "851 - 日常测试\n872 - 短线王续费近120天到期",
      "popup": 0,
      "click": 0,
      "purchaseClick": 0,
      "order": 0,
      "deal": 0,
      "material": "续费送好礼，福利直接领",
      "updatedAt": "2026-06-10 02:21",
      "rawId": 374061
    },
    {
      "date": "2026-06-13",
      "project": "短线王续费",
      "channel": "APP",
      "adType": "",
      "adTypeName": "全部广告类型",
      "bannerType": 1,
      "adId": "239107",
      "title": "短线王续费",
      "audience": "851 - 日常测试\n872 - 短线王续费近120天到期",
      "popup": 0,
      "click": 0,
      "purchaseClick": 0,
      "order": 0,
      "deal": 0,
      "material": "短线王续费",
      "updatedAt": "2026-06-10 02:21",
      "rawId": 374062
    },
    {
      "date": "2026-06-13",
      "project": "短线王续费",
      "channel": "APP",
      "adType": "",
      "adTypeName": "全部广告类型",
      "bannerType": 1,
      "adId": "239108",
      "title": "短线王续费",
      "audience": "851 - 日常测试\n872 - 短线王续费近120天到期",
      "popup": 0,
      "click": 2,
      "purchaseClick": 2,
      "order": 2,
      "deal": 0,
      "material": "短线王续费",
      "updatedAt": "2026-06-14 02:20",
      "rawId": 374063
    },
    {
      "date": "2026-06-13",
      "project": "短线王续费",
      "channel": "APP",
      "adType": "",
      "adTypeName": "全部广告类型",
      "bannerType": 1,
      "adId": "239109",
      "title": "续费送好礼，福利直接领",
      "audience": "872 - 短线王续费近120天到期",
      "popup": 0,
      "click": 0,
      "purchaseClick": 0,
      "order": 0,
      "deal": 0,
      "material": "续费送好礼，福利直接领",
      "updatedAt": "2026-06-10 02:21",
      "rawId": 374064
    },
    {
      "date": "2026-06-13",
      "project": "短线王续费",
      "channel": "APP",
      "adType": "",
      "adTypeName": "全部广告类型",
      "bannerType": 1,
      "adId": "239110",
      "title": "短线王续费",
      "audience": "851 - 日常测试\n872 - 短线王续费近120天到期",
      "popup": 0,
      "click": 0,
      "purchaseClick": 0,
      "order": 0,
      "deal": 0,
      "material": "短线王续费",
      "updatedAt": "2026-06-10 02:21",
      "rawId": 374065
    },
    {
      "date": "2026-06-13",
      "project": "短线王续费",
      "channel": "APP",
      "adType": "",
      "adTypeName": "全部广告类型",
      "bannerType": 1,
      "adId": "239111",
      "title": "短线王续费",
      "audience": "851 - 日常测试\n872 - 短线王续费近120天到期",
      "popup": 0,
      "click": 0,
      "purchaseClick": 0,
      "order": 0,
      "deal": 0,
      "material": "短线王续费",
      "updatedAt": "2026-06-10 02:21",
      "rawId": 374066
    },
    {
      "date": "2026-06-13",
      "project": "短线王续费",
      "channel": "APP",
      "adType": "",
      "adTypeName": "全部广告类型",
      "bannerType": 1,
      "adId": "239112",
      "title": "点击查看",
      "audience": "872 - 短线王续费近120天到期",
      "popup": 0,
      "click": 0,
      "purchaseClick": 0,
      "order": 0,
      "deal": 0,
      "material": "点击查看",
      "updatedAt": "2026-06-10 02:21",
      "rawId": 374067
    },
    {
      "date": "2026-06-13",
      "project": "短线王续费",
      "channel": "APP",
      "adType": "",
      "adTypeName": "全部广告类型",
      "bannerType": 1,
      "adId": "239113",
      "title": "续费送好礼，福利直接领",
      "audience": "872 - 短线王续费近120天到期\n851 - 日常测试",
      "popup": 0,
      "click": 0,
      "purchaseClick": 0,
      "order": 0,
      "deal": 0,
      "material": "续费送好礼，福利直接领",
      "updatedAt": "2026-06-10 02:21",
      "rawId": 374068
    },
    {
      "date": "2026-06-13",
      "project": "短线王续费",
      "channel": "APP",
      "adType": "",
      "adTypeName": "全部广告类型",
      "bannerType": 1,
      "adId": "239114",
      "title": "续费送好礼，福利直接领",
      "audience": "872 - 短线王续费近120天到期\n851 - 日常测试",
      "popup": 0,
      "click": 0,
      "purchaseClick": 0,
      "order": 0,
      "deal": 0,
      "material": "续费送好礼，福利直接领",
      "updatedAt": "2026-06-10 02:21",
      "rawId": 374069
    },
    {
      "date": "2026-06-13",
      "project": "短线王续费",
      "channel": "APP",
      "adType": "",
      "adTypeName": "全部广告类型",
      "bannerType": 1,
      "adId": "239115",
      "title": "短线王续费",
      "audience": "872 - 短线王续费近120天到期",
      "popup": 0,
      "click": 0,
      "purchaseClick": 0,
      "order": 0,
      "deal": 0,
      "material": "短线王续费",
      "updatedAt": "2026-06-10 02:21",
      "rawId": 374070
    },
    {
      "date": "2026-06-13",
      "project": "短线王续费",
      "channel": "APP",
      "adType": "",
      "adTypeName": "全部广告类型",
      "bannerType": 1,
      "adId": "239116",
      "title": "短线王续费",
      "audience": "872 - 短线王续费近120天到期",
      "popup": 0,
      "click": 0,
      "purchaseClick": 0,
      "order": 0,
      "deal": 0,
      "material": "短线王续费",
      "updatedAt": "2026-06-10 02:21",
      "rawId": 374071
    },
    {
      "date": "2026-06-13",
      "project": "短线王续费",
      "channel": "APP",
      "adType": "",
      "adTypeName": "全部广告类型",
      "bannerType": 1,
      "adId": "239117",
      "title": "短线王续费",
      "audience": "872 - 短线王续费近120天到期",
      "popup": 0,
      "click": 0,
      "purchaseClick": 0,
      "order": 0,
      "deal": 0,
      "material": "短线王续费",
      "updatedAt": "2026-06-10 02:21",
      "rawId": 374072
    },
    {
      "date": "2026-06-13",
      "project": "短线王续费",
      "channel": "APP",
      "adType": "",
      "adTypeName": "全部广告类型",
      "bannerType": 1,
      "adId": "239118",
      "title": "点击查看",
      "audience": "872 - 短线王续费近120天到期",
      "popup": 0,
      "click": 3,
      "purchaseClick": 1,
      "order": 1,
      "deal": 0,
      "material": "点击查看",
      "updatedAt": "2026-06-13 12:01",
      "rawId": 374073
    },
    {
      "date": "2026-06-13",
      "project": "短线王续费",
      "channel": "APP",
      "adType": "",
      "adTypeName": "全部广告类型",
      "bannerType": 1,
      "adId": "239119",
      "title": "点击查看",
      "audience": "872 - 短线王续费近120天到期",
      "popup": 0,
      "click": 1,
      "purchaseClick": 0,
      "order": 0,
      "deal": 0,
      "material": "点击查看",
      "updatedAt": "2026-06-14 02:20",
      "rawId": 374074
    },
    {
      "date": "2026-06-13",
      "project": "短线王续费",
      "channel": "APP",
      "adType": "",
      "adTypeName": "全部广告类型",
      "bannerType": 1,
      "adId": "239120",
      "title": "点击查看",
      "audience": "872 - 短线王续费近120天到期",
      "popup": 0,
      "click": 3,
      "purchaseClick": 0,
      "order": 0,
      "deal": 0,
      "material": "点击查看",
      "updatedAt": "2026-06-14 02:20",
      "rawId": 374075
    },
    {
      "date": "2026-06-13",
      "project": "短线王续费",
      "channel": "APP",
      "adType": "",
      "adTypeName": "全部广告类型",
      "bannerType": 1,
      "adId": "239121",
      "title": "短线王续费",
      "audience": "613 - 短线王已过期用户\n851 - 日常测试",
      "popup": 0,
      "click": 0,
      "purchaseClick": 0,
      "order": 0,
      "deal": 0,
      "material": "短线王续费",
      "updatedAt": "2026-06-10 02:21",
      "rawId": 374076
    },
    {
      "date": "2026-06-13",
      "project": "短线王续费",
      "channel": "APP",
      "adType": "",
      "adTypeName": "全部广告类型",
      "bannerType": 1,
      "adId": "239122",
      "title": "短线王续费",
      "audience": "613 - 短线王已过期用户\n851 - 日常测试",
      "popup": 0,
      "click": 0,
      "purchaseClick": 0,
      "order": 0,
      "deal": 0,
      "material": "短线王续费",
      "updatedAt": "2026-06-10 02:21",
      "rawId": 374077
    },
    {
      "date": "2026-06-13",
      "project": "短线王续费",
      "channel": "APP",
      "adType": "",
      "adTypeName": "全部广告类型",
      "bannerType": 1,
      "adId": "239123",
      "title": "短线王续费",
      "audience": "613 - 短线王已过期用户\n851 - 日常测试",
      "popup": 0,
      "click": 1,
      "purchaseClick": 1,
      "order": 1,
      "deal": 0,
      "material": "短线王续费",
      "updatedAt": "2026-06-14 02:20",
      "rawId": 374078
    },
    {
      "date": "2026-06-13",
      "project": "短线王续费",
      "channel": "APP",
      "adType": "",
      "adTypeName": "全部广告类型",
      "bannerType": 1,
      "adId": "239124",
      "title": "短线王续费",
      "audience": "613 - 短线王已过期用户\n851 - 日常测试",
      "popup": 0,
      "click": 1,
      "purchaseClick": 0,
      "order": 0,
      "deal": 0,
      "material": "短线王续费",
      "updatedAt": "2026-06-14 02:20",
      "rawId": 374079
    },
    {
      "date": "2026-06-13",
      "project": "短线王续费",
      "channel": "APP",
      "adType": "",
      "adTypeName": "全部广告类型",
      "bannerType": 1,
      "adId": "239125",
      "title": "短线王续费",
      "audience": "613 - 短线王已过期用户\n851 - 日常测试",
      "popup": 0,
      "click": 0,
      "purchaseClick": 0,
      "order": 0,
      "deal": 0,
      "material": "短线王续费",
      "updatedAt": "2026-06-10 02:21",
      "rawId": 374080
    },
    {
      "date": "2026-06-13",
      "project": "短线王续费",
      "channel": "APP",
      "adType": "",
      "adTypeName": "全部广告类型",
      "bannerType": 1,
      "adId": "239126",
      "title": "短线王续费",
      "audience": "613 - 短线王已过期用户\n851 - 日常测试",
      "popup": 0,
      "click": 0,
      "purchaseClick": 0,
      "order": 0,
      "deal": 0,
      "material": "短线王续费",
      "updatedAt": "2026-06-10 02:21",
      "rawId": 374081
    },
    {
      "date": "2026-06-13",
      "project": "短线王续费",
      "channel": "APP",
      "adType": "",
      "adTypeName": "全部广告类型",
      "bannerType": 1,
      "adId": "239127",
      "title": "续费送好礼，福利直接领",
      "audience": "613 - 短线王已过期用户\n851 - 日常测试",
      "popup": 0,
      "click": 0,
      "purchaseClick": 0,
      "order": 0,
      "deal": 0,
      "material": "续费送好礼，福利直接领",
      "updatedAt": "2026-06-10 02:21",
      "rawId": 374082
    },
    {
      "date": "2026-06-13",
      "project": "短线王续费",
      "channel": "APP",
      "adType": "",
      "adTypeName": "全部广告类型",
      "bannerType": 1,
      "adId": "239128",
      "title": "续费送好礼，福利直接领",
      "audience": "613 - 短线王已过期用户\n851 - 日常测试",
      "popup": 0,
      "click": 0,
      "purchaseClick": 0,
      "order": 0,
      "deal": 0,
      "material": "续费送好礼，福利直接领",
      "updatedAt": "2026-06-10 02:21",
      "rawId": 374083
    },
    {
      "date": "2026-06-13",
      "project": "短线王续费",
      "channel": "APP",
      "adType": "",
      "adTypeName": "全部广告类型",
      "bannerType": 1,
      "adId": "239129",
      "title": "短线王续费",
      "audience": "613 - 短线王已过期用户\n851 - 日常测试",
      "popup": 0,
      "click": 0,
      "purchaseClick": 0,
      "order": 0,
      "deal": 0,
      "material": "短线王续费",
      "updatedAt": "2026-06-10 02:21",
      "rawId": 374084
    },
    {
      "date": "2026-06-13",
      "project": "短线王续费",
      "channel": "APP",
      "adType": "",
      "adTypeName": "全部广告类型",
      "bannerType": 1,
      "adId": "239130",
      "title": "短线王续费",
      "audience": "613 - 短线王已过期用户\n851 - 日常测试",
      "popup": 0,
      "click": 1,
      "purchaseClick": 1,
      "order": 1,
      "deal": 0,
      "material": "短线王续费",
      "updatedAt": "2026-06-13 12:01",
      "rawId": 374085
    },
    {
      "date": "2026-06-13",
      "project": "短线王续费",
      "channel": "APP",
      "adType": "",
      "adTypeName": "全部广告类型",
      "bannerType": 1,
      "adId": "239131",
      "title": "续费送好礼，福利直接领",
      "audience": "613 - 短线王已过期用户",
      "popup": 0,
      "click": 0,
      "purchaseClick": 0,
      "order": 0,
      "deal": 0,
      "material": "续费送好礼，福利直接领",
      "updatedAt": "2026-06-10 02:21",
      "rawId": 374086
    },
    {
      "date": "2026-06-13",
      "project": "短线王续费",
      "channel": "APP",
      "adType": "",
      "adTypeName": "全部广告类型",
      "bannerType": 1,
      "adId": "239132",
      "title": "短线王续费",
      "audience": "613 - 短线王已过期用户\n851 - 日常测试",
      "popup": 0,
      "click": 0,
      "purchaseClick": 0,
      "order": 0,
      "deal": 0,
      "material": "短线王续费",
      "updatedAt": "2026-06-10 02:21",
      "rawId": 374087
    },
    {
      "date": "2026-06-13",
      "project": "短线王续费",
      "channel": "APP",
      "adType": "",
      "adTypeName": "全部广告类型",
      "bannerType": 1,
      "adId": "239133",
      "title": "短线王续费",
      "audience": "613 - 短线王已过期用户\n851 - 日常测试",
      "popup": 0,
      "click": 0,
      "purchaseClick": 0,
      "order": 0,
      "deal": 0,
      "material": "短线王续费",
      "updatedAt": "2026-06-10 02:21",
      "rawId": 374088
    },
    {
      "date": "2026-06-13",
      "project": "短线王续费",
      "channel": "APP",
      "adType": "",
      "adTypeName": "全部广告类型",
      "bannerType": 1,
      "adId": "239134",
      "title": "点击查看",
      "audience": "613 - 短线王已过期用户",
      "popup": 0,
      "click": 0,
      "purchaseClick": 0,
      "order": 0,
      "deal": 0,
      "material": "点击查看",
      "updatedAt": "2026-06-10 02:21",
      "rawId": 374089
    },
    {
      "date": "2026-06-13",
      "project": "短线王续费",
      "channel": "APP",
      "adType": "",
      "adTypeName": "全部广告类型",
      "bannerType": 1,
      "adId": "239135",
      "title": "续费送好礼，福利直接领",
      "audience": "613 - 短线王已过期用户\n851 - 日常测试",
      "popup": 0,
      "click": 0,
      "purchaseClick": 0,
      "order": 0,
      "deal": 0,
      "material": "续费送好礼，福利直接领",
      "updatedAt": "2026-06-10 02:21",
      "rawId": 374090
    },
    {
      "date": "2026-06-13",
      "project": "短线王续费",
      "channel": "APP",
      "adType": "",
      "adTypeName": "全部广告类型",
      "bannerType": 1,
      "adId": "239136",
      "title": "续费送好礼，福利直接领",
      "audience": "613 - 短线王已过期用户\n851 - 日常测试",
      "popup": 0,
      "click": 0,
      "purchaseClick": 0,
      "order": 0,
      "deal": 0,
      "material": "续费送好礼，福利直接领",
      "updatedAt": "2026-06-10 02:21",
      "rawId": 374091
    },
    {
      "date": "2026-06-13",
      "project": "短线王续费",
      "channel": "APP",
      "adType": "",
      "adTypeName": "全部广告类型",
      "bannerType": 1,
      "adId": "239137",
      "title": "短线王续费",
      "audience": "613 - 短线王已过期用户",
      "popup": 0,
      "click": 0,
      "purchaseClick": 0,
      "order": 0,
      "deal": 0,
      "material": "短线王续费",
      "updatedAt": "2026-06-10 02:21",
      "rawId": 374092
    },
    {
      "date": "2026-06-13",
      "project": "短线王续费",
      "channel": "APP",
      "adType": "",
      "adTypeName": "全部广告类型",
      "bannerType": 1,
      "adId": "239138",
      "title": "短线王续费",
      "audience": "613 - 短线王已过期用户",
      "popup": 0,
      "click": 0,
      "purchaseClick": 0,
      "order": 0,
      "deal": 0,
      "material": "短线王续费",
      "updatedAt": "2026-06-10 02:21",
      "rawId": 374093
    },
    {
      "date": "2026-06-13",
      "project": "短线王续费",
      "channel": "APP",
      "adType": "",
      "adTypeName": "全部广告类型",
      "bannerType": 1,
      "adId": "239139",
      "title": "短线王续费",
      "audience": "613 - 短线王已过期用户",
      "popup": 0,
      "click": 0,
      "purchaseClick": 0,
      "order": 0,
      "deal": 0,
      "material": "短线王续费",
      "updatedAt": "2026-06-10 02:21",
      "rawId": 374094
    },
    {
      "date": "2026-06-13",
      "project": "短线王续费",
      "channel": "APP",
      "adType": "",
      "adTypeName": "全部广告类型",
      "bannerType": 1,
      "adId": "239140",
      "title": "点击查看",
      "audience": "613 - 短线王已过期用户",
      "popup": 0,
      "click": 3,
      "purchaseClick": 1,
      "order": 1,
      "deal": 0,
      "material": "点击查看",
      "updatedAt": "2026-06-13 12:01",
      "rawId": 374095
    },
    {
      "date": "2026-06-13",
      "project": "短线王续费",
      "channel": "APP",
      "adType": "",
      "adTypeName": "全部广告类型",
      "bannerType": 1,
      "adId": "239141",
      "title": "点击查看",
      "audience": "613 - 短线王已过期用户",
      "popup": 0,
      "click": 2,
      "purchaseClick": 1,
      "order": 1,
      "deal": 1,
      "material": "点击查看",
      "updatedAt": "2026-06-14 02:20",
      "rawId": 374096
    },
    {
      "date": "2026-06-13",
      "project": "短线王续费",
      "channel": "APP",
      "adType": "",
      "adTypeName": "全部广告类型",
      "bannerType": 1,
      "adId": "239142",
      "title": "点击查看",
      "audience": "613 - 短线王已过期用户",
      "popup": 0,
      "click": 1,
      "purchaseClick": 0,
      "order": 0,
      "deal": 0,
      "material": "点击查看",
      "updatedAt": "2026-06-14 02:20",
      "rawId": 374097
    },
    {
      "date": "2026-06-13",
      "project": "短线王续费",
      "channel": "APP",
      "adType": "",
      "adTypeName": "全部广告类型",
      "bannerType": 1,
      "adId": "248000",
      "title": "短线王续费",
      "audience": "1454 - 营销策划测试分组\n872 - 短线王续费近120天到期",
      "popup": 0,
      "click": 1,
      "purchaseClick": 0,
      "order": 0,
      "deal": 0,
      "material": "短线王续费",
      "updatedAt": "2026-06-13 02:23",
      "rawId": 381614
    },
    {
      "date": "2026-06-13",
      "project": "短线王续费",
      "channel": "APP",
      "adType": "",
      "adTypeName": "全部广告类型",
      "bannerType": 1,
      "adId": "248001",
      "title": "短线王续费",
      "audience": "1454 - 营销策划测试分组\n872 - 短线王续费近120天到期",
      "popup": 0,
      "click": 1,
      "purchaseClick": 1,
      "order": 1,
      "deal": 0,
      "material": "短线王续费",
      "updatedAt": "2026-06-13 02:23",
      "rawId": 381615
    },
    {
      "date": "2026-06-13",
      "project": "短线王续费",
      "channel": "APP",
      "adType": "",
      "adTypeName": "全部广告类型",
      "bannerType": 1,
      "adId": "248002",
      "title": "短线王续费",
      "audience": "872 - 短线王续费近120天到期\n1454 - 营销策划测试分组",
      "popup": 0,
      "click": 0,
      "purchaseClick": 0,
      "order": 0,
      "deal": 0,
      "material": "短线王续费",
      "updatedAt": "2026-06-08 02:33",
      "rawId": 381616
    },
    {
      "date": "2026-06-13",
      "project": "短线王续费",
      "channel": "APP",
      "adType": "",
      "adTypeName": "全部广告类型",
      "bannerType": 1,
      "adId": "248003",
      "title": "短线王续费",
      "audience": "1454 - 营销策划测试分组\n872 - 短线王续费近120天到期",
      "popup": 0,
      "click": 0,
      "purchaseClick": 0,
      "order": 0,
      "deal": 0,
      "material": "短线王续费",
      "updatedAt": "2026-06-08 02:33",
      "rawId": 381617
    },
    {
      "date": "2026-06-13",
      "project": "短线王续费",
      "channel": "APP",
      "adType": "",
      "adTypeName": "全部广告类型",
      "bannerType": 1,
      "adId": "248004",
      "title": "短线王续费",
      "audience": "613 - 短线王已过期用户\n1454 - 营销策划测试分组",
      "popup": 0,
      "click": 0,
      "purchaseClick": 0,
      "order": 0,
      "deal": 0,
      "material": "短线王续费",
      "updatedAt": "2026-06-08 02:33",
      "rawId": 381618
    },
    {
      "date": "2026-06-13",
      "project": "短线王续费",
      "channel": "APP",
      "adType": "",
      "adTypeName": "全部广告类型",
      "bannerType": 1,
      "adId": "248005",
      "title": "短线王续费",
      "audience": "613 - 短线王已过期用户\n1454 - 营销策划测试分组",
      "popup": 0,
      "click": 1,
      "purchaseClick": 1,
      "order": 1,
      "deal": 0,
      "material": "短线王续费",
      "updatedAt": "2026-06-13 12:04",
      "rawId": 381619
    },
    {
      "date": "2026-06-13",
      "project": "短线王续费",
      "channel": "APP",
      "adType": "",
      "adTypeName": "全部广告类型",
      "bannerType": 1,
      "adId": "248006",
      "title": "短线王续费",
      "audience": "613 - 短线王已过期用户\n1454 - 营销策划测试分组",
      "popup": 0,
      "click": 0,
      "purchaseClick": 0,
      "order": 0,
      "deal": 0,
      "material": "短线王续费",
      "updatedAt": "2026-06-08 02:33",
      "rawId": 381620
    },
    {
      "date": "2026-06-13",
      "project": "短线王续费",
      "channel": "APP",
      "adType": "",
      "adTypeName": "全部广告类型",
      "bannerType": 1,
      "adId": "248007",
      "title": "短线王续费",
      "audience": "613 - 短线王已过期用户\n1454 - 营销策划测试分组",
      "popup": 0,
      "click": 0,
      "purchaseClick": 0,
      "order": 0,
      "deal": 0,
      "material": "短线王续费",
      "updatedAt": "2026-06-08 02:33",
      "rawId": 381621
    },
    {
      "date": "2026-06-13",
      "project": "短线王续费",
      "channel": "APP",
      "adType": "",
      "adTypeName": "全部广告类型",
      "bannerType": 1,
      "adId": "248367",
      "title": "短线王年终福利",
      "audience": "613 - 短线王已过期用户",
      "popup": 0,
      "click": 0,
      "purchaseClick": 0,
      "order": 0,
      "deal": 0,
      "material": "短线王年终福利",
      "updatedAt": "2026-06-10 02:31",
      "rawId": 382452
    },
    {
      "date": "2026-06-13",
      "project": "短线王续费",
      "channel": "APP",
      "adType": "",
      "adTypeName": "全部广告类型",
      "bannerType": 1,
      "adId": "248368",
      "title": "短线王年终福利",
      "audience": "872 - 短线王续费近120天到期",
      "popup": 0,
      "click": 0,
      "purchaseClick": 0,
      "order": 0,
      "deal": 0,
      "material": "短线王年终福利",
      "updatedAt": "2026-06-10 02:31",
      "rawId": 382453
    },
    {
      "date": "2026-06-13",
      "project": "短线王续费",
      "channel": "APP",
      "adType": "",
      "adTypeName": "全部广告类型",
      "bannerType": 2,
      "adId": "250946",
      "title": "短线王续费",
      "audience": "613 - 短线王已过期用户\n851 - 日常测试",
      "popup": 217,
      "click": 12,
      "purchaseClick": 12,
      "order": 12,
      "deal": 0,
      "material": "短线王续费",
      "updatedAt": "2026-06-14 02:29",
      "rawId": 386072
    },
    {
      "date": "2026-06-13",
      "project": "短线王续费",
      "channel": "APP",
      "adType": "",
      "adTypeName": "全部广告类型",
      "bannerType": 2,
      "adId": "250947",
      "title": "短线王续费",
      "audience": "851 - 日常测试\n3311 - 0-90天内过期短线王",
      "popup": 189,
      "click": 9,
      "purchaseClick": 8,
      "order": 7,
      "deal": 0,
      "material": "短线王续费",
      "updatedAt": "2026-06-14 02:29",
      "rawId": 386073
    },
    {
      "date": "2026-06-13",
      "project": "短线王续费",
      "channel": "APP",
      "adType": "",
      "adTypeName": "全部广告类型",
      "bannerType": 2,
      "adId": "250948",
      "title": "短线王续费",
      "audience": "851 - 日常测试\n3312 - 91-120天过期短线王续费",
      "popup": 86,
      "click": 3,
      "purchaseClick": 2,
      "order": 2,
      "deal": 0,
      "material": "短线王续费",
      "updatedAt": "2026-06-14 02:29",
      "rawId": 386074
    },
    {
      "date": "2026-06-13",
      "project": "短线王续费",
      "channel": "APP",
      "adType": "",
      "adTypeName": "全部广告类型",
      "bannerType": 2,
      "adId": "250949",
      "title": "短线王续费",
      "audience": "613 - 短线王已过期用户\n851 - 日常测试",
      "popup": 6,
      "click": 1,
      "purchaseClick": 1,
      "order": 1,
      "deal": 0,
      "material": "短线王续费",
      "updatedAt": "2026-06-14 02:29",
      "rawId": 386075
    },
    {
      "date": "2026-06-13",
      "project": "短线王续费",
      "channel": "APP",
      "adType": "",
      "adTypeName": "全部广告类型",
      "bannerType": 2,
      "adId": "250950",
      "title": "短线王续费",
      "audience": "613 - 短线王已过期用户\n851 - 日常测试",
      "popup": 1,
      "click": 0,
      "purchaseClick": 0,
      "order": 0,
      "deal": 0,
      "material": "短线王续费",
      "updatedAt": "2026-06-14 02:29",
      "rawId": 386076
    },
    {
      "date": "2026-06-13",
      "project": "短线王续费",
      "channel": "APP",
      "adType": "",
      "adTypeName": "全部广告类型",
      "bannerType": 2,
      "adId": "250951",
      "title": "短线王续费",
      "audience": "851 - 日常测试\n3311 - 0-90天内过期短线王",
      "popup": 1,
      "click": 0,
      "purchaseClick": 0,
      "order": 0,
      "deal": 0,
      "material": "短线王续费",
      "updatedAt": "2026-06-14 02:29",
      "rawId": 386077
    },
    {
      "date": "2026-06-13",
      "project": "短线王续费",
      "channel": "APP",
      "adType": "",
      "adTypeName": "全部广告类型",
      "bannerType": 2,
      "adId": "250952",
      "title": "短线王续费",
      "audience": "851 - 日常测试\n3312 - 91-120天过期短线王续费",
      "popup": 1,
      "click": 0,
      "purchaseClick": 0,
      "order": 0,
      "deal": 0,
      "material": "短线王续费",
      "updatedAt": "2026-06-14 02:29",
      "rawId": 386078
    },
    {
      "date": "2026-06-13",
      "project": "短线王续费",
      "channel": "APP",
      "adType": "",
      "adTypeName": "全部广告类型",
      "bannerType": 2,
      "adId": "250953",
      "title": "短线王续费",
      "audience": "613 - 短线王已过期用户\n851 - 日常测试",
      "popup": 10,
      "click": 1,
      "purchaseClick": 1,
      "order": 1,
      "deal": 0,
      "material": "短线王续费",
      "updatedAt": "2026-06-14 02:29",
      "rawId": 386079
    },
    {
      "date": "2026-06-13",
      "project": "短线王续费",
      "channel": "APP",
      "adType": "",
      "adTypeName": "全部广告类型",
      "bannerType": 2,
      "adId": "250954",
      "title": "短线王续费",
      "audience": "851 - 日常测试\n3311 - 0-90天内过期短线王",
      "popup": 11,
      "click": 1,
      "purchaseClick": 1,
      "order": 1,
      "deal": 0,
      "material": "短线王续费",
      "updatedAt": "2026-06-14 02:29",
      "rawId": 386080
    },
    {
      "date": "2026-06-13",
      "project": "短线王续费",
      "channel": "APP",
      "adType": "",
      "adTypeName": "全部广告类型",
      "bannerType": 2,
      "adId": "250955",
      "title": "短线王续费",
      "audience": "851 - 日常测试\n3312 - 91-120天过期短线王续费",
      "popup": 4,
      "click": 1,
      "purchaseClick": 1,
      "order": 1,
      "deal": 0,
      "material": "短线王续费",
      "updatedAt": "2026-06-14 02:29",
      "rawId": 386081
    },
    {
      "date": "2026-06-13",
      "project": "短线王续费",
      "channel": "APP",
      "adType": "",
      "adTypeName": "全部广告类型",
      "bannerType": 2,
      "adId": "250956",
      "title": "短线王续费",
      "audience": "613 - 短线王已过期用户\n851 - 日常测试",
      "popup": 69,
      "click": 8,
      "purchaseClick": 8,
      "order": 8,
      "deal": 0,
      "material": "短线王续费",
      "updatedAt": "2026-06-14 02:29",
      "rawId": 386082
    },
    {
      "date": "2026-06-13",
      "project": "短线王续费",
      "channel": "APP",
      "adType": "",
      "adTypeName": "全部广告类型",
      "bannerType": 2,
      "adId": "250957",
      "title": "短线王续费",
      "audience": "851 - 日常测试\n3311 - 0-90天内过期短线王",
      "popup": 74,
      "click": 5,
      "purchaseClick": 4,
      "order": 4,
      "deal": 0,
      "material": "短线王续费",
      "updatedAt": "2026-06-14 02:29",
      "rawId": 386083
    },
    {
      "date": "2026-06-13",
      "project": "短线王续费",
      "channel": "APP",
      "adType": "",
      "adTypeName": "全部广告类型",
      "bannerType": 2,
      "adId": "250958",
      "title": "短线王续费",
      "audience": "851 - 日常测试\n3312 - 91-120天过期短线王续费",
      "popup": 30,
      "click": 2,
      "purchaseClick": 2,
      "order": 1,
      "deal": 0,
      "material": "短线王续费",
      "updatedAt": "2026-06-14 02:29",
      "rawId": 386084
    },
    {
      "date": "2026-06-13",
      "project": "短线王续费",
      "channel": "APP",
      "adType": "",
      "adTypeName": "全部广告类型",
      "bannerType": 2,
      "adId": "250959",
      "title": "短线王续费",
      "audience": "613 - 短线王已过期用户\n851 - 日常测试",
      "popup": 6,
      "click": 1,
      "purchaseClick": 1,
      "order": 1,
      "deal": 0,
      "material": "短线王续费",
      "updatedAt": "2026-06-14 02:29",
      "rawId": 386085
    },
    {
      "date": "2026-06-13",
      "project": "短线王续费",
      "channel": "APP",
      "adType": "",
      "adTypeName": "全部广告类型",
      "bannerType": 2,
      "adId": "250960",
      "title": "短线王续费",
      "audience": "613 - 短线王已过期用户\n851 - 日常测试",
      "popup": 105,
      "click": 7,
      "purchaseClick": 6,
      "order": 6,
      "deal": 0,
      "material": "短线王续费",
      "updatedAt": "2026-06-14 02:29",
      "rawId": 386086
    },
    {
      "date": "2026-06-13",
      "project": "短线王续费",
      "channel": "APP",
      "adType": "",
      "adTypeName": "全部广告类型",
      "bannerType": 2,
      "adId": "250961",
      "title": "短线王续费",
      "audience": "851 - 日常测试\n3311 - 0-90天内过期短线王",
      "popup": 111,
      "click": 7,
      "purchaseClick": 7,
      "order": 7,
      "deal": 0,
      "material": "短线王续费",
      "updatedAt": "2026-06-14 02:29",
      "rawId": 386087
    },
    {
      "date": "2026-06-13",
      "project": "短线王续费",
      "channel": "APP",
      "adType": "",
      "adTypeName": "全部广告类型",
      "bannerType": 2,
      "adId": "250962",
      "title": "短线王续费",
      "audience": "851 - 日常测试\n3312 - 91-120天过期短线王续费",
      "popup": 43,
      "click": 3,
      "purchaseClick": 3,
      "order": 3,
      "deal": 0,
      "material": "短线王续费",
      "updatedAt": "2026-06-14 02:29",
      "rawId": 386088
    },
    {
      "date": "2026-06-13",
      "project": "短线王续费",
      "channel": "APP",
      "adType": "",
      "adTypeName": "全部广告类型",
      "bannerType": 2,
      "adId": "250963",
      "title": "短线王续费",
      "audience": "613 - 短线王已过期用户\n851 - 日常测试",
      "popup": 115,
      "click": 4,
      "purchaseClick": 4,
      "order": 3,
      "deal": 0,
      "material": "短线王续费",
      "updatedAt": "2026-06-14 02:29",
      "rawId": 386089
    },
    {
      "date": "2026-06-13",
      "project": "短线王续费",
      "channel": "APP",
      "adType": "",
      "adTypeName": "全部广告类型",
      "bannerType": 2,
      "adId": "250964",
      "title": "短线王续费",
      "audience": "851 - 日常测试\n3311 - 0-90天内过期短线王",
      "popup": 125,
      "click": 9,
      "purchaseClick": 9,
      "order": 8,
      "deal": 0,
      "material": "短线王续费",
      "updatedAt": "2026-06-14 02:29",
      "rawId": 386090
    },
    {
      "date": "2026-06-13",
      "project": "短线王续费",
      "channel": "APP",
      "adType": "",
      "adTypeName": "全部广告类型",
      "bannerType": 2,
      "adId": "250965",
      "title": "短线王续费",
      "audience": "851 - 日常测试\n3312 - 91-120天过期短线王续费",
      "popup": 48,
      "click": 4,
      "purchaseClick": 4,
      "order": 4,
      "deal": 0,
      "material": "短线王续费",
      "updatedAt": "2026-06-14 02:29",
      "rawId": 386091
    },
    {
      "date": "2026-06-13",
      "project": "短线王续费",
      "channel": "APP",
      "adType": "",
      "adTypeName": "全部广告类型",
      "bannerType": 2,
      "adId": "250966",
      "title": "短线王续费",
      "audience": "613 - 短线王已过期用户\n851 - 日常测试",
      "popup": 16,
      "click": 1,
      "purchaseClick": 1,
      "order": 1,
      "deal": 0,
      "material": "短线王续费",
      "updatedAt": "2026-06-14 02:29",
      "rawId": 386092
    },
    {
      "date": "2026-06-13",
      "project": "短线王续费",
      "channel": "APP",
      "adType": "",
      "adTypeName": "全部广告类型",
      "bannerType": 3,
      "adId": "66694",
      "title": "你的自选股突破在即？",
      "audience": "613 - 短线王已过期用户\n851 - 日常测试\n872 - 短线王续费近120天到期",
      "popup": 712,
      "click": 30,
      "purchaseClick": 29,
      "order": 25,
      "deal": 0,
      "material": "你的自选股突破在即？",
      "updatedAt": "2026-06-14 02:33",
      "rawId": 385921
    },
    {
      "date": "2026-06-13",
      "project": "短线王续费",
      "channel": "APP",
      "adType": "",
      "adTypeName": "全部广告类型",
      "bannerType": 3,
      "adId": "66695",
      "title": "您有一笔福利即将失效！",
      "audience": "613 - 短线王已过期用户\n851 - 日常测试\n872 - 短线王续费近120天到期",
      "popup": 700,
      "click": 18,
      "purchaseClick": 19,
      "order": 16,
      "deal": 1,
      "material": "您有一笔福利即将失效！",
      "updatedAt": "2026-06-14 02:33",
      "rawId": 385922
    },
    {
      "date": "2026-06-13",
      "project": "短线王续费",
      "channel": "APP",
      "adType": "",
      "adTypeName": "全部广告类型",
      "bannerType": 3,
      "adId": "67108",
      "title": "短线王过期提醒",
      "audience": "4343 - 【短线王续费】当天过期用户",
      "popup": 0,
      "click": 0,
      "purchaseClick": 0,
      "order": 0,
      "deal": 0,
      "material": "短线王过期提醒",
      "updatedAt": "2026-06-14 02:34",
      "rawId": 386179
    },
    {
      "date": "2026-06-13",
      "project": "短线王续费",
      "channel": "APP",
      "adType": "",
      "adTypeName": "全部广告类型",
      "bannerType": 3,
      "adId": "67109",
      "title": "短线王过期提醒",
      "audience": "4345 - 【短线王续费】7天前过期的用户",
      "popup": 0,
      "click": 0,
      "purchaseClick": 0,
      "order": 0,
      "deal": 0,
      "material": "短线王过期提醒",
      "updatedAt": "2026-06-14 02:34",
      "rawId": 386180
    },
    {
      "date": "2026-06-13",
      "project": "短线王续费",
      "channel": "APP",
      "adType": "",
      "adTypeName": "全部广告类型",
      "bannerType": 3,
      "adId": "67110",
      "title": "短线王即将过期提醒",
      "audience": "1988 - 【短线王续费】90天后过期用户",
      "popup": 2,
      "click": 0,
      "purchaseClick": 0,
      "order": 0,
      "deal": 0,
      "material": "短线王即将过期提醒",
      "updatedAt": "2026-06-14 02:34",
      "rawId": 386181
    },
    {
      "date": "2026-06-13",
      "project": "短线王续费",
      "channel": "APP",
      "adType": "",
      "adTypeName": "全部广告类型",
      "bannerType": 3,
      "adId": "67111",
      "title": "短线王即将过期提醒",
      "audience": "1989 - 【短线王续费】60天后过期用户",
      "popup": 6,
      "click": 0,
      "purchaseClick": 0,
      "order": 0,
      "deal": 0,
      "material": "短线王即将过期提醒",
      "updatedAt": "2026-06-14 02:34",
      "rawId": 386182
    },
    {
      "date": "2026-06-13",
      "project": "短线王续费",
      "channel": "APP",
      "adType": "",
      "adTypeName": "全部广告类型",
      "bannerType": 3,
      "adId": "67112",
      "title": "短线王即将过期提醒",
      "audience": "1990 - 【短线王续费】30天后过期用户",
      "popup": 4,
      "click": 0,
      "purchaseClick": 0,
      "order": 0,
      "deal": 0,
      "material": "短线王即将过期提醒",
      "updatedAt": "2026-06-14 02:34",
      "rawId": 386183
    },
    {
      "date": "2026-06-13",
      "project": "短线王续费",
      "channel": "APP",
      "adType": "",
      "adTypeName": "全部广告类型",
      "bannerType": 3,
      "adId": "67113",
      "title": "短线王即将过期提醒",
      "audience": "1991 - 【短线王续费】20天后过期用户",
      "popup": 2,
      "click": 0,
      "purchaseClick": 0,
      "order": 0,
      "deal": 0,
      "material": "短线王即将过期提醒",
      "updatedAt": "2026-06-14 02:34",
      "rawId": 386184
    },
    {
      "date": "2026-06-13",
      "project": "短线王续费",
      "channel": "APP",
      "adType": "",
      "adTypeName": "全部广告类型",
      "bannerType": 3,
      "adId": "67114",
      "title": "短线王即将过期提醒",
      "audience": "1992 - 【短线王续费】10天后过期用户",
      "popup": 3,
      "click": 0,
      "purchaseClick": 0,
      "order": 0,
      "deal": 0,
      "material": "短线王即将过期提醒",
      "updatedAt": "2026-06-14 02:34",
      "rawId": 386185
    },
    {
      "date": "2026-06-13",
      "project": "短线王续费",
      "channel": "APP",
      "adType": "",
      "adTypeName": "全部广告类型",
      "bannerType": 3,
      "adId": "67115",
      "title": "短线王即将过期提醒",
      "audience": "1993 - 【短线王续费】7天后过期用户",
      "popup": 1,
      "click": 0,
      "purchaseClick": 0,
      "order": 0,
      "deal": 0,
      "material": "短线王即将过期提醒",
      "updatedAt": "2026-06-14 02:34",
      "rawId": 386186
    },
    {
      "date": "2026-06-13",
      "project": "短线王续费",
      "channel": "APP",
      "adType": "",
      "adTypeName": "全部广告类型",
      "bannerType": 3,
      "adId": "67116",
      "title": "短线王过期提醒",
      "audience": "4344 - 【短线王续费】3天前过期的用户",
      "popup": 2,
      "click": 0,
      "purchaseClick": 0,
      "order": 0,
      "deal": 0,
      "material": "短线王过期提醒",
      "updatedAt": "2026-06-14 02:34",
      "rawId": 386187
    },
    {
      "date": "2026-06-13",
      "project": "短线王续费",
      "channel": "APP",
      "adType": "",
      "adTypeName": "全部广告类型",
      "bannerType": 3,
      "adId": "67117",
      "title": "短线王即将过期提醒",
      "audience": "4326 - 【短线王续费】3天后当天过期用户",
      "popup": 3,
      "click": 0,
      "purchaseClick": 0,
      "order": 0,
      "deal": 0,
      "material": "短线王即将过期提醒",
      "updatedAt": "2026-06-14 02:34",
      "rawId": 386188
    },
    {
      "date": "2026-06-13",
      "project": "短线王续费",
      "channel": "APP",
      "adType": "",
      "adTypeName": "全部广告类型",
      "bannerType": 3,
      "adId": "67118",
      "title": "短线王即将过期提醒",
      "audience": "4325 - 【短线王续费】2天后当天过期用户",
      "popup": 2,
      "click": 0,
      "purchaseClick": 0,
      "order": 0,
      "deal": 0,
      "material": "短线王即将过期提醒",
      "updatedAt": "2026-06-14 02:34",
      "rawId": 386189
    },
    {
      "date": "2026-06-13",
      "project": "短线王续费",
      "channel": "APP",
      "adType": "",
      "adTypeName": "全部广告类型",
      "bannerType": 3,
      "adId": "67119",
      "title": "短线王即将过期提醒",
      "audience": "4324 - 【短线王续费】1天后当天过期用户",
      "popup": 3,
      "click": 0,
      "purchaseClick": 0,
      "order": 0,
      "deal": 0,
      "material": "短线王即将过期提醒",
      "updatedAt": "2026-06-13 12:16",
      "rawId": 385955
    },
    {
      "date": "2026-06-13",
      "project": "短线王续费",
      "channel": "PC",
      "adType": "",
      "adTypeName": "全部广告类型",
      "bannerType": 4,
      "adId": "106185",
      "title": "短线王续费",
      "audience": "613 - 短线王已过期用户\n851 - 日常测试",
      "popup": 132,
      "click": 5,
      "purchaseClick": 5,
      "order": 5,
      "deal": 0,
      "material": "短线王续费",
      "updatedAt": "2026-06-13 12:18",
      "rawId": 385914
    },
    {
      "date": "2026-06-13",
      "project": "短线王续费",
      "channel": "PC",
      "adType": "",
      "adTypeName": "全部广告类型",
      "bannerType": 4,
      "adId": "106186",
      "title": "短线王续费",
      "audience": "3311 - 0-90天内过期短线王",
      "popup": 81,
      "click": 3,
      "purchaseClick": 3,
      "order": 3,
      "deal": 0,
      "material": "短线王续费",
      "updatedAt": "2026-06-13 12:18",
      "rawId": 385915
    },
    {
      "date": "2026-06-13",
      "project": "短线王续费",
      "channel": "PC",
      "adType": "",
      "adTypeName": "全部广告类型",
      "bannerType": 4,
      "adId": "106187",
      "title": "短线王续费",
      "audience": "3312 - 91-120天过期短线王续费",
      "popup": 36,
      "click": 0,
      "purchaseClick": 0,
      "order": 0,
      "deal": 0,
      "material": "短线王续费",
      "updatedAt": "2026-06-13 12:18",
      "rawId": 385916
    },
    {
      "date": "2026-06-13",
      "project": "短线王续费",
      "channel": "PC",
      "adType": "",
      "adTypeName": "全部广告类型",
      "bannerType": 4,
      "adId": "106188",
      "title": "短线王续费",
      "audience": "613 - 短线王已过期用户\n851 - 日常测试",
      "popup": 140,
      "click": 6,
      "purchaseClick": 6,
      "order": 6,
      "deal": 0,
      "material": "短线王续费",
      "updatedAt": "2026-06-13 12:18",
      "rawId": 385981
    },
    {
      "date": "2026-06-13",
      "project": "短线王续费",
      "channel": "PC",
      "adType": "",
      "adTypeName": "全部广告类型",
      "bannerType": 4,
      "adId": "106189",
      "title": "短线王续费",
      "audience": "3311 - 0-90天内过期短线王",
      "popup": 86,
      "click": 3,
      "purchaseClick": 3,
      "order": 3,
      "deal": 0,
      "material": "短线王续费",
      "updatedAt": "2026-06-13 12:18",
      "rawId": 385982
    },
    {
      "date": "2026-06-13",
      "project": "短线王续费",
      "channel": "PC",
      "adType": "",
      "adTypeName": "全部广告类型",
      "bannerType": 4,
      "adId": "106190",
      "title": "短线王续费",
      "audience": "3312 - 91-120天过期短线王续费",
      "popup": 37,
      "click": 2,
      "purchaseClick": 2,
      "order": 2,
      "deal": 0,
      "material": "短线王续费",
      "updatedAt": "2026-06-13 12:18",
      "rawId": 385983
    },
    {
      "date": "2026-06-13",
      "project": "短线王续费",
      "channel": "PC",
      "adType": "",
      "adTypeName": "全部广告类型",
      "bannerType": 4,
      "adId": "106191",
      "title": "短线王续费",
      "audience": "613 - 短线王已过期用户\n851 - 日常测试",
      "popup": 168,
      "click": 2,
      "purchaseClick": 2,
      "order": 2,
      "deal": 0,
      "material": "短线王续费",
      "updatedAt": "2026-06-14 02:35",
      "rawId": 386219
    },
    {
      "date": "2026-06-13",
      "project": "短线王续费",
      "channel": "PC",
      "adType": "",
      "adTypeName": "全部广告类型",
      "bannerType": 4,
      "adId": "106192",
      "title": "短线王续费",
      "audience": "3311 - 0-90天内过期短线王",
      "popup": 120,
      "click": 5,
      "purchaseClick": 5,
      "order": 5,
      "deal": 2,
      "material": "短线王续费",
      "updatedAt": "2026-06-14 02:35",
      "rawId": 386220
    },
    {
      "date": "2026-06-13",
      "project": "短线王续费",
      "channel": "PC",
      "adType": "",
      "adTypeName": "全部广告类型",
      "bannerType": 4,
      "adId": "106193",
      "title": "短线王续费",
      "audience": "3312 - 91-120天过期短线王续费",
      "popup": 46,
      "click": 1,
      "purchaseClick": 1,
      "order": 1,
      "deal": 0,
      "material": "短线王续费",
      "updatedAt": "2026-06-14 02:35",
      "rawId": 386221
    },
    {
      "date": "2026-06-13",
      "project": "短线王续费",
      "channel": "PC",
      "adType": "",
      "adTypeName": "全部广告类型",
      "bannerType": 4,
      "adId": "106194",
      "title": "短线王续费",
      "audience": "613 - 短线王已过期用户\n851 - 日常测试",
      "popup": 146,
      "click": 1,
      "purchaseClick": 1,
      "order": 1,
      "deal": 0,
      "material": "短线王续费",
      "updatedAt": "2026-06-14 02:35",
      "rawId": 386222
    },
    {
      "date": "2026-06-13",
      "project": "短线王续费",
      "channel": "PC",
      "adType": "",
      "adTypeName": "全部广告类型",
      "bannerType": 4,
      "adId": "106195",
      "title": "短线王续费",
      "audience": "3311 - 0-90天内过期短线王",
      "popup": 114,
      "click": 5,
      "purchaseClick": 5,
      "order": 5,
      "deal": 1,
      "material": "短线王续费",
      "updatedAt": "2026-06-14 02:35",
      "rawId": 386223
    },
    {
      "date": "2026-06-13",
      "project": "短线王续费",
      "channel": "PC",
      "adType": "",
      "adTypeName": "全部广告类型",
      "bannerType": 4,
      "adId": "106196",
      "title": "短线王续费",
      "audience": "3312 - 91-120天过期短线王续费",
      "popup": 44,
      "click": 1,
      "purchaseClick": 1,
      "order": 1,
      "deal": 0,
      "material": "短线王续费",
      "updatedAt": "2026-06-14 02:35",
      "rawId": 386224
    },
    {
      "date": "2026-06-13",
      "project": "短线王续费",
      "channel": "PC",
      "adType": "",
      "adTypeName": "全部广告类型",
      "bannerType": 4,
      "adId": "106197",
      "title": "提醒！",
      "audience": "613 - 短线王已过期用户\n851 - 日常测试",
      "popup": 142,
      "click": 2,
      "purchaseClick": 2,
      "order": 2,
      "deal": 0,
      "material": "提醒！",
      "updatedAt": "2026-06-14 02:35",
      "rawId": 385984
    },
    {
      "date": "2026-06-13",
      "project": "短线王续费",
      "channel": "PC",
      "adType": "",
      "adTypeName": "全部广告类型",
      "bannerType": 4,
      "adId": "106198",
      "title": "【紧急】",
      "audience": "3311 - 0-90天内过期短线王",
      "popup": 95,
      "click": 2,
      "purchaseClick": 2,
      "order": 2,
      "deal": 0,
      "material": "【紧急】",
      "updatedAt": "2026-06-14 02:35",
      "rawId": 385985
    },
    {
      "date": "2026-06-13",
      "project": "短线王续费",
      "channel": "PC",
      "adType": "",
      "adTypeName": "全部广告类型",
      "bannerType": 4,
      "adId": "106199",
      "title": "补贴已到账！",
      "audience": "3312 - 91-120天过期短线王续费",
      "popup": 42,
      "click": 1,
      "purchaseClick": 1,
      "order": 1,
      "deal": 0,
      "material": "补贴已到账！",
      "updatedAt": "2026-06-14 02:35",
      "rawId": 385986
    },
    {
      "date": "2026-06-13",
      "project": "短线王续费",
      "channel": "PC",
      "adType": "",
      "adTypeName": "全部广告类型",
      "bannerType": 4,
      "adId": "106200",
      "title": "【最新发现】",
      "audience": "613 - 短线王已过期用户\n851 - 日常测试",
      "popup": 140,
      "click": 1,
      "purchaseClick": 1,
      "order": 1,
      "deal": 0,
      "material": "【最新发现】",
      "updatedAt": "2026-06-14 02:35",
      "rawId": 386225
    },
    {
      "date": "2026-06-13",
      "project": "短线王续费",
      "channel": "PC",
      "adType": "",
      "adTypeName": "全部广告类型",
      "bannerType": 4,
      "adId": "106201",
      "title": "【注意】",
      "audience": "3311 - 0-90天内过期短线王",
      "popup": 107,
      "click": 3,
      "purchaseClick": 3,
      "order": 3,
      "deal": 0,
      "material": "【注意】",
      "updatedAt": "2026-06-14 02:35",
      "rawId": 386226
    },
    {
      "date": "2026-06-13",
      "project": "短线王续费",
      "channel": "PC",
      "adType": "",
      "adTypeName": "全部广告类型",
      "bannerType": 4,
      "adId": "106202",
      "title": "【突发】",
      "audience": "3312 - 91-120天过期短线王续费",
      "popup": 44,
      "click": 0,
      "purchaseClick": 0,
      "order": 0,
      "deal": 0,
      "material": "【突发】",
      "updatedAt": "2026-06-14 02:35",
      "rawId": 386227
    }
  ],
  "snapshots": [
    {
      "updatedAt": "2026-07-09T11:27:34.678Z",
      "projectName": "短线王新开",
      "backendProjectName": "短线王新开",
      "groupId": 7,
      "adType": "",
      "adTypeName": "全部广告类型",
      "bannerType": 1,
      "appScope": "ALL",
      "appScopeName": "全部",
      "backendAppNames": "PC+APP",
      "rowCount": 52,
      "summary": [
        {
          "date": "2026-06-13",
          "status": 200,
          "code": 1,
          "msg": "成功",
          "total": 23,
          "count": 23
        },
        {
          "date": "2026-06-13",
          "status": 200,
          "code": 1,
          "msg": "成功",
          "total": 9,
          "count": 9
        },
        {
          "date": "2026-06-13",
          "status": 200,
          "code": 1,
          "msg": "成功",
          "total": 4,
          "count": 4
        },
        {
          "date": "2026-06-13",
          "status": 200,
          "code": 1,
          "msg": "成功",
          "total": 16,
          "count": 16
        }
      ]
    },
    {
      "updatedAt": "2026-07-09T11:38:55.692Z",
      "projectName": "短线王续费",
      "backendProjectName": "短线王续费",
      "groupId": 27,
      "adType": "",
      "adTypeName": "全部广告类型",
      "bannerType": 1,
      "appScope": "ALL",
      "appScopeName": "全部",
      "backendAppNames": "PC+APP",
      "rowCount": 115,
      "summary": [
        {
          "date": "2026-06-13",
          "status": 200,
          "code": 1,
          "msg": "成功",
          "total": 62,
          "count": 62
        },
        {
          "date": "2026-06-13",
          "status": 200,
          "code": 1,
          "msg": "成功",
          "total": 21,
          "count": 21
        },
        {
          "date": "2026-06-13",
          "status": 200,
          "code": 1,
          "msg": "成功",
          "total": 14,
          "count": 14
        },
        {
          "date": "2026-06-13",
          "status": 200,
          "code": 1,
          "msg": "成功",
          "total": 18,
          "count": 18
        }
      ]
    }
  ]
}